d3s/__init__.py
d3s/nagios.py
d3s/units.py
d3s/nagios_plugins/__init__.py
d3s/nagios_plugins/check_health.py
d3s/nagios_plugins/check_memory.py
d3s/nagios_plugins/check_os_updates.py
d3s/nagios_plugins/check_systemd_service.py
d3s_nagios_plugins-1.0.4.dist-info/licenses/LICENSE
d3s_nagios_plugins-1.0.4.dist-info/METADATA
d3s_nagios_plugins-1.0.4.dist-info/WHEEL
d3s_nagios_plugins-1.0.4.dist-info/entry_points.txt
d3s_nagios_plugins-1.0.4.dist-info/top_level.txt
d3s_nagios_plugins-1.0.4.dist-info/RECORD
