Metadata-Version: 2.4
Name: d3s-nagios-plugins
Version: 1.0.4
Summary: Collection of various Nagios plugins
Home-page: https://github.com/d-iii-s/d3s-nagios-plugins
Author: Vojtech Horky
Author-email: horky@d3s.mff.cuni.cz
License: Apache-2.0
Keywords: Nagios monitoring
Requires-Python: >=3.8
License-File: LICENSE
Dynamic: license-file
